CHANGES.txt
LICENSE.txt
MANIFEST.in
README.txt
setup.py
js/__init__.py
js.jquery_elastic.egg-info/PKG-INFO
js.jquery_elastic.egg-info/SOURCES.txt
js.jquery_elastic.egg-info/dependency_links.txt
js.jquery_elastic.egg-info/entry_points.txt
js.jquery_elastic.egg-info/namespace_packages.txt
js.jquery_elastic.egg-info/not-zip-safe
js.jquery_elastic.egg-info/requires.txt
js.jquery_elastic.egg-info/top_level.txt
js/jquery_elastic/__init__.py
js/jquery_elastic/test_jquery_elastic.txt
js/jquery_elastic/resources/jquery.elastic.source.js