Metadata-Version: 1.0
Name: js.jquery-elastic
Version: 1.6.11
Summary: Fanstatic packaging of jQuery Elastic
Home-page: UNKNOWN
Author: Fanstatic Developers
Author-email: fanstatic@googlegroups.com
License: BSD
Platform: UNKNOWN
